fakebalance.py
fakebalance-1.0.0.dist-info/WHEEL
fakebalance-1.0.0.dist-info/METADATA
fakebalance-1.0.0.dist-info/RECORD
