Metadata-Version: 2.1
Name: fakebalance
Version: 1.0.0
Summary: fakebalance qiwi\sber
Author: Ilya Romanov
Author-email: rolton-tv@mail.ru
Requires-Python: >=3.8,<4.0
Classifier: Programming Language :: Python :: 3
Classifier: Programming Language :: Python :: 3.8
Classifier: Programming Language :: Python :: 3.9
